{
  "n_texts": 230,
  "min_tokens": 2,
  "max_tokens": 5,
  "mean_tokens": 3.639130434782609,
  "median_tokens": 4.0,
  "token_count_distribution": {
    "2": 6,
    "3": 89,
    "4": 117,
    "5": 18
  },
  "items": [
    {
      "text": "احتمال",
      "n_tokens": 4,
      "token_ids": [
        2,
        12332,
        15816,
        1821
      ],
      "tokens": [
        "<bos>",
        "اح",
        "تم",
        "ال"
      ]
    },
    {
      "text": "اختطاف",
      "n_tokens": 4,
      "token_ids": [
        2,
        27879,
        125849,
        8744
      ],
      "tokens": [
        "<bos>",
        "اخت",
        "ط",
        "اف"
      ]
    },
    {
      "text": "ارتفاع",
      "n_tokens": 3,
      "token_ids": [
        2,
        28058,
        42476
      ],
      "tokens": [
        "<bos>",
        "ارت",
        "فاع"
      ]
    },
    {
      "text": "استبعد",
      "n_tokens": 3,
      "token_ids": [
        2,
        15860,
        64677
      ],
      "tokens": [
        "<bos>",
        "است",
        "بعد"
      ]
    },
    {
      "text": "استبنص",
      "n_tokens": 4,
      "token_ids": [
        2,
        15860,
        58854,
        125822
      ],
      "tokens": [
        "<bos>",
        "است",
        "بن",
        "ص"
      ]
    },
    {
      "text": "استتدغ",
      "n_tokens": 5,
      "token_ids": [
        2,
        15860,
        125698,
        125697,
        126036
      ],
      "tokens": [
        "<bos>",
        "است",
        "ت",
        "د",
        "غ"
      ]
    },
    {
      "text": "استثمخ",
      "n_tokens": 4,
      "token_ids": [
        2,
        15860,
        101088,
        125792
      ],
      "tokens": [
        "<bos>",
        "است",
        "ثم",
        "خ"
      ]
    },
    {
      "text": "استثمر",
      "n_tokens": 4,
      "token_ids": [
        2,
        15860,
        126051,
        12883
      ],
      "tokens": [
        "<bos>",
        "است",
        "ث",
        "مر"
      ]
    },
    {
      "text": "استجبص",
      "n_tokens": 4,
      "token_ids": [
        2,
        15860,
        35035,
        125822
      ],
      "tokens": [
        "<bos>",
        "است",
        "جب",
        "ص"
      ]
    },
    {
      "text": "استجفق",
      "n_tokens": 4,
      "token_ids": [
        2,
        15860,
        125773,
        33305
      ],
      "tokens": [
        "<bos>",
        "است",
        "ج",
        "فق"
      ]
    },
    {
      "text": "استحذس",
      "n_tokens": 5,
      "token_ids": [
        2,
        15860,
        125769,
        126008,
        125716
      ],
      "tokens": [
        "<bos>",
        "است",
        "ح",
        "ذ",
        "س"
      ]
    },
    {
      "text": "استخدم",
      "n_tokens": 3,
      "token_ids": [
        2,
        15860,
        39734
      ],
      "tokens": [
        "<bos>",
        "است",
        "خدم"
      ]
    },
    {
      "text": "استخفص",
      "n_tokens": 5,
      "token_ids": [
        2,
        15860,
        125792,
        125734,
        125822
      ],
      "tokens": [
        "<bos>",
        "است",
        "خ",
        "ف",
        "ص"
      ]
    },
    {
      "text": "استخلص",
      "n_tokens": 3,
      "token_ids": [
        2,
        15860,
        98037
      ],
      "tokens": [
        "<bos>",
        "است",
        "خلص"
      ]
    },
    {
      "text": "استدغز",
      "n_tokens": 5,
      "token_ids": [
        2,
        15860,
        125697,
        126036,
        125770
      ],
      "tokens": [
        "<bos>",
        "است",
        "د",
        "غ",
        "ز"
      ]
    },
    {
      "text": "استدقس",
      "n_tokens": 5,
      "token_ids": [
        2,
        15860,
        125697,
        125756,
        125716
      ],
      "tokens": [
        "<bos>",
        "است",
        "د",
        "ق",
        "س"
      ]
    },
    {
      "text": "استذحج",
      "n_tokens": 5,
      "token_ids": [
        2,
        15860,
        126008,
        125769,
        125773
      ],
      "tokens": [
        "<bos>",
        "است",
        "ذ",
        "ح",
        "ج"
      ]
    },
    {
      "text": "استشظق",
      "n_tokens": 5,
      "token_ids": [
        2,
        15860,
        125746,
        126210,
        125756
      ],
      "tokens": [
        "<bos>",
        "است",
        "ش",
        "ظ",
        "ق"
      ]
    },
    {
      "text": "استطغد",
      "n_tokens": 5,
      "token_ids": [
        2,
        15860,
        125849,
        126036,
        125697
      ],
      "tokens": [
        "<bos>",
        "است",
        "ط",
        "غ",
        "د"
      ]
    },
    {
      "text": "استعمر",
      "n_tokens": 4,
      "token_ids": [
        2,
        15860,
        125724,
        12883
      ],
      "tokens": [
        "<bos>",
        "است",
        "ع",
        "مر"
      ]
    },
    {
      "text": "استغرق",
      "n_tokens": 4,
      "token_ids": [
        2,
        15860,
        126036,
        29361
      ],
      "tokens": [
        "<bos>",
        "است",
        "غ",
        "رق"
      ]
    },
    {
      "text": "استغشط",
      "n_tokens": 5,
      "token_ids": [
        2,
        15860,
        126036,
        125746,
        125849
      ],
      "tokens": [
        "<bos>",
        "است",
        "غ",
        "ش",
        "ط"
      ]
    },
    {
      "text": "استفجز",
      "n_tokens": 4,
      "token_ids": [
        2,
        15860,
        125734,
        50514
      ],
      "tokens": [
        "<bos>",
        "است",
        "ف",
        "جز"
      ]
    },
    {
      "text": "استفغش",
      "n_tokens": 5,
      "token_ids": [
        2,
        15860,
        125734,
        126036,
        125746
      ],
      "tokens": [
        "<bos>",
        "است",
        "ف",
        "غ",
        "ش"
      ]
    },
    {
      "text": "استقطب",
      "n_tokens": 4,
      "token_ids": [
        2,
        15860,
        22037,
        125705
      ],
      "tokens": [
        "<bos>",
        "است",
        "قط",
        "ب"
      ]
    },
    {
      "text": "استقهث",
      "n_tokens": 4,
      "token_ids": [
        2,
        15860,
        21354,
        126051
      ],
      "tokens": [
        "<bos>",
        "است",
        "قه",
        "ث"
      ]
    },
    {
      "text": "استكغف",
      "n_tokens": 5,
      "token_ids": [
        2,
        15860,
        125780,
        126036,
        125734
      ],
      "tokens": [
        "<bos>",
        "است",
        "ك",
        "غ",
        "ف"
      ]
    },
    {
      "text": "استلام",
      "n_tokens": 3,
      "token_ids": [
        2,
        15860,
        9936
      ],
      "tokens": [
        "<bos>",
        "است",
        "لام"
      ]
    },
    {
      "text": "استمدص",
      "n_tokens": 4,
      "token_ids": [
        2,
        15860,
        12111,
        125822
      ],
      "tokens": [
        "<bos>",
        "است",
        "مد",
        "ص"
      ]
    },
    {
      "text": "استمسك",
      "n_tokens": 4,
      "token_ids": [
        2,
        15860,
        24339,
        125780
      ],
      "tokens": [
        "<bos>",
        "است",
        "مس",
        "ك"
      ]
    },
    {
      "text": "استنتج",
      "n_tokens": 4,
      "token_ids": [
        2,
        15860,
        17319,
        125773
      ],
      "tokens": [
        "<bos>",
        "است",
        "نت",
        "ج"
      ]
    },
    {
      "text": "استنسخ",
      "n_tokens": 4,
      "token_ids": [
        2,
        15860,
        22116,
        125792
      ],
      "tokens": [
        "<bos>",
        "است",
        "نس",
        "خ"
      ]
    },
    {
      "text": "استنفغ",
      "n_tokens": 4,
      "token_ids": [
        2,
        15860,
        71296,
        126036
      ],
      "tokens": [
        "<bos>",
        "است",
        "نف",
        "غ"
      ]
    },
    {
      "text": "استهزخ",
      "n_tokens": 5,
      "token_ids": [
        2,
        15860,
        125706,
        125770,
        125792
      ],
      "tokens": [
        "<bos>",
        "است",
        "ه",
        "ز",
        "خ"
      ]
    },
    {
      "text": "اشتعال",
      "n_tokens": 3,
      "token_ids": [
        2,
        24256,
        101699
      ],
      "tokens": [
        "<bos>",
        "اشت",
        "عال"
      ]
    },
    {
      "text": "افتراس",
      "n_tokens": 3,
      "token_ids": [
        2,
        38335,
        97888
      ],
      "tokens": [
        "<bos>",
        "افت",
        "راس"
      ]
    },
    {
      "text": "اقتصاد",
      "n_tokens": 2,
      "token_ids": [
        2,
        72474
      ],
      "tokens": [
        "<bos>",
        "اقتصاد"
      ]
    },
    {
      "text": "اقتناع",
      "n_tokens": 3,
      "token_ids": [
        2,
        60119,
        115346
      ],
      "tokens": [
        "<bos>",
        "اقت",
        "ناع"
      ]
    },
    {
      "text": "التماس",
      "n_tokens": 3,
      "token_ids": [
        2,
        21214,
        48049
      ],
      "tokens": [
        "<bos>",
        "الت",
        "ماس"
      ]
    },
    {
      "text": "انبسط",
      "n_tokens": 4,
      "token_ids": [
        2,
        1613,
        125705,
        67982
      ],
      "tokens": [
        "<bos>",
        "ان",
        "ب",
        "سط"
      ]
    },
    {
      "text": "انحسم",
      "n_tokens": 4,
      "token_ids": [
        2,
        1613,
        125769,
        11488
      ],
      "tokens": [
        "<bos>",
        "ان",
        "ح",
        "سم"
      ]
    },
    {
      "text": "انحصر",
      "n_tokens": 4,
      "token_ids": [
        2,
        1613,
        125769,
        27407
      ],
      "tokens": [
        "<bos>",
        "ان",
        "ح",
        "صر"
      ]
    },
    {
      "text": "اندفع",
      "n_tokens": 3,
      "token_ids": [
        2,
        24988,
        33041
      ],
      "tokens": [
        "<bos>",
        "اند",
        "فع"
      ]
    },
    {
      "text": "انعقد",
      "n_tokens": 4,
      "token_ids": [
        2,
        1613,
        125724,
        10555
      ],
      "tokens": [
        "<bos>",
        "ان",
        "ع",
        "قد"
      ]
    },
    {
      "text": "انفتح",
      "n_tokens": 3,
      "token_ids": [
        2,
        1613,
        99952
      ],
      "tokens": [
        "<bos>",
        "ان",
        "فتح"
      ]
    },
    {
      "text": "انقبض",
      "n_tokens": 4,
      "token_ids": [
        2,
        1613,
        50182,
        125957
      ],
      "tokens": [
        "<bos>",
        "ان",
        "قب",
        "ض"
      ]
    },
    {
      "text": "انقطع",
      "n_tokens": 3,
      "token_ids": [
        2,
        1613,
        100208
      ],
      "tokens": [
        "<bos>",
        "ان",
        "قطع"
      ]
    },
    {
      "text": "انكتب",
      "n_tokens": 3,
      "token_ids": [
        2,
        1613,
        58320
      ],
      "tokens": [
        "<bos>",
        "ان",
        "كتب"
      ]
    },
    {
      "text": "انكسر",
      "n_tokens": 4,
      "token_ids": [
        2,
        1613,
        125780,
        24588
      ],
      "tokens": [
        "<bos>",
        "ان",
        "ك",
        "سر"
      ]
    },
    {
      "text": "اهتمام",
      "n_tokens": 3,
      "token_ids": [
        2,
        7241,
        74108
      ],
      "tokens": [
        "<bos>",
        "اه",
        "تمام"
      ]
    },
    {
      "text": "بانص",
      "n_tokens": 3,
      "token_ids": [
        2,
        37178,
        125822
      ],
      "tokens": [
        "<bos>",
        "بان",
        "ص"
      ]
    },
    {
      "text": "بناص",
      "n_tokens": 4,
      "token_ids": [
        2,
        125705,
        6212,
        125822
      ],
      "tokens": [
        "<bos>",
        "ب",
        "نا",
        "ص"
      ]
    },
    {
      "text": "بنوص",
      "n_tokens": 3,
      "token_ids": [
        2,
        58854,
        28228
      ],
      "tokens": [
        "<bos>",
        "بن",
        "وص"
      ]
    },
    {
      "text": "تادغ",
      "n_tokens": 4,
      "token_ids": [
        2,
        125698,
        3369,
        126036
      ],
      "tokens": [
        "<bos>",
        "ت",
        "اد",
        "غ"
      ]
    },
    {
      "text": "تجار",
      "n_tokens": 3,
      "token_ids": [
        2,
        125698,
        57352
      ],
      "tokens": [
        "<bos>",
        "ت",
        "جار"
      ]
    },
    {
      "text": "تجارة",
      "n_tokens": 3,
      "token_ids": [
        2,
        94247,
        40135
      ],
      "tokens": [
        "<bos>",
        "تج",
        "ارة"
      ]
    },
    {
      "text": "تداغ",
      "n_tokens": 4,
      "token_ids": [
        2,
        125698,
        15082,
        126036
      ],
      "tokens": [
        "<bos>",
        "ت",
        "دا",
        "غ"
      ]
    },
    {
      "text": "تدوغ",
      "n_tokens": 4,
      "token_ids": [
        2,
        125698,
        58976,
        126036
      ],
      "tokens": [
        "<bos>",
        "ت",
        "دو",
        "غ"
      ]
    },
    {
      "text": "ثامخ",
      "n_tokens": 4,
      "token_ids": [
        2,
        126051,
        2900,
        125792
      ],
      "tokens": [
        "<bos>",
        "ث",
        "ام",
        "خ"
      ]
    },
    {
      "text": "ثقال",
      "n_tokens": 3,
      "token_ids": [
        2,
        126051,
        26393
      ],
      "tokens": [
        "<bos>",
        "ث",
        "قال"
      ]
    },
    {
      "text": "ثقيل",
      "n_tokens": 4,
      "token_ids": [
        2,
        126051,
        125756,
        8994
      ],
      "tokens": [
        "<bos>",
        "ث",
        "ق",
        "يل"
      ]
    },
    {
      "text": "ثماخ",
      "n_tokens": 4,
      "token_ids": [
        2,
        126051,
        5079,
        125792
      ],
      "tokens": [
        "<bos>",
        "ث",
        "ما",
        "خ"
      ]
    },
    {
      "text": "ثمار",
      "n_tokens": 2,
      "token_ids": [
        2,
        120205
      ],
      "tokens": [
        "<bos>",
        "ثمار"
      ]
    },
    {
      "text": "ثموخ",
      "n_tokens": 4,
      "token_ids": [
        2,
        126051,
        43067,
        125792
      ],
      "tokens": [
        "<bos>",
        "ث",
        "مو",
        "خ"
      ]
    },
    {
      "text": "جابص",
      "n_tokens": 3,
      "token_ids": [
        2,
        78890,
        125822
      ],
      "tokens": [
        "<bos>",
        "جاب",
        "ص"
      ]
    },
    {
      "text": "جافق",
      "n_tokens": 4,
      "token_ids": [
        2,
        125773,
        8744,
        125756
      ],
      "tokens": [
        "<bos>",
        "ج",
        "اف",
        "ق"
      ]
    },
    {
      "text": "جباص",
      "n_tokens": 3,
      "token_ids": [
        2,
        35035,
        15836
      ],
      "tokens": [
        "<bos>",
        "جب",
        "اص"
      ]
    },
    {
      "text": "جبال",
      "n_tokens": 3,
      "token_ids": [
        2,
        125773,
        24958
      ],
      "tokens": [
        "<bos>",
        "ج",
        "بال"
      ]
    },
    {
      "text": "جبوص",
      "n_tokens": 4,
      "token_ids": [
        2,
        125773,
        8617,
        125822
      ],
      "tokens": [
        "<bos>",
        "ج",
        "بو",
        "ص"
      ]
    },
    {
      "text": "جدارة",
      "n_tokens": 3,
      "token_ids": [
        2,
        125773,
        71573
      ],
      "tokens": [
        "<bos>",
        "ج",
        "دارة"
      ]
    },
    {
      "text": "جديد",
      "n_tokens": 3,
      "token_ids": [
        2,
        36244,
        7514
      ],
      "tokens": [
        "<bos>",
        "جد",
        "يد"
      ]
    },
    {
      "text": "جفاق",
      "n_tokens": 3,
      "token_ids": [
        2,
        125773,
        50183
      ],
      "tokens": [
        "<bos>",
        "ج",
        "فاق"
      ]
    },
    {
      "text": "جفوق",
      "n_tokens": 4,
      "token_ids": [
        2,
        125773,
        125734,
        12415
      ],
      "tokens": [
        "<bos>",
        "ج",
        "ف",
        "وق"
      ]
    },
    {
      "text": "جمار",
      "n_tokens": 3,
      "token_ids": [
        2,
        16105,
        1897
      ],
      "tokens": [
        "<bos>",
        "جم",
        "ار"
      ]
    },
    {
      "text": "جميل",
      "n_tokens": 3,
      "token_ids": [
        2,
        16105,
        8994
      ],
      "tokens": [
        "<bos>",
        "جم",
        "يل"
      ]
    },
    {
      "text": "جهلاء",
      "n_tokens": 3,
      "token_ids": [
        2,
        20838,
        55352
      ],
      "tokens": [
        "<bos>",
        "جه",
        "لاء"
      ]
    },
    {
      "text": "حاذس",
      "n_tokens": 4,
      "token_ids": [
        2,
        125769,
        79882,
        125716
      ],
      "tokens": [
        "<bos>",
        "ح",
        "اذ",
        "س"
      ]
    },
    {
      "text": "حالم",
      "n_tokens": 3,
      "token_ids": [
        2,
        125769,
        12305
      ],
      "tokens": [
        "<bos>",
        "ح",
        "الم"
      ]
    },
    {
      "text": "حدود",
      "n_tokens": 3,
      "token_ids": [
        2,
        12400,
        4167
      ],
      "tokens": [
        "<bos>",
        "حد",
        "ود"
      ]
    },
    {
      "text": "حذاس",
      "n_tokens": 4,
      "token_ids": [
        2,
        125769,
        126008,
        7146
      ],
      "tokens": [
        "<bos>",
        "ح",
        "ذ",
        "اس"
      ]
    },
    {
      "text": "حذوس",
      "n_tokens": 4,
      "token_ids": [
        2,
        125769,
        126008,
        12402
      ],
      "tokens": [
        "<bos>",
        "ح",
        "ذ",
        "وس"
      ]
    },
    {
      "text": "حراثة",
      "n_tokens": 4,
      "token_ids": [
        2,
        125769,
        2263,
        45175
      ],
      "tokens": [
        "<bos>",
        "ح",
        "را",
        "ثة"
      ]
    },
    {
      "text": "حصاده",
      "n_tokens": 3,
      "token_ids": [
        2,
        81799,
        13508
      ],
      "tokens": [
        "<bos>",
        "حص",
        "اده"
      ]
    },
    {
      "text": "حقول",
      "n_tokens": 3,
      "token_ids": [
        2,
        125769,
        41397
      ],
      "tokens": [
        "<bos>",
        "ح",
        "قول"
      ]
    },
    {
      "text": "خاطف",
      "n_tokens": 4,
      "token_ids": [
        2,
        125792,
        14843,
        125734
      ],
      "tokens": [
        "<bos>",
        "خ",
        "اط",
        "ف"
      ]
    },
    {
      "text": "خافص",
      "n_tokens": 4,
      "token_ids": [
        2,
        125792,
        8744,
        125822
      ],
      "tokens": [
        "<bos>",
        "خ",
        "اف",
        "ص"
      ]
    },
    {
      "text": "خجلان",
      "n_tokens": 4,
      "token_ids": [
        2,
        125792,
        32072,
        1613
      ],
      "tokens": [
        "<bos>",
        "خ",
        "جل",
        "ان"
      ]
    },
    {
      "text": "خفاص",
      "n_tokens": 4,
      "token_ids": [
        2,
        125792,
        125734,
        15836
      ],
      "tokens": [
        "<bos>",
        "خ",
        "ف",
        "اص"
      ]
    },
    {
      "text": "خفوص",
      "n_tokens": 4,
      "token_ids": [
        2,
        125792,
        125734,
        28228
      ],
      "tokens": [
        "<bos>",
        "خ",
        "ف",
        "وص"
      ]
    },
    {
      "text": "خفيف",
      "n_tokens": 3,
      "token_ids": [
        2,
        125792,
        100537
      ],
      "tokens": [
        "<bos>",
        "خ",
        "فيف"
      ]
    },
    {
      "text": "خلفاء",
      "n_tokens": 4,
      "token_ids": [
        2,
        125792,
        15277,
        11373
      ],
      "tokens": [
        "<bos>",
        "خ",
        "لف",
        "اء"
      ]
    },
    {
      "text": "داغز",
      "n_tokens": 4,
      "token_ids": [
        2,
        15082,
        126036,
        125770
      ],
      "tokens": [
        "<bos>",
        "دا",
        "غ",
        "ز"
      ]
    },
    {
      "text": "داقس",
      "n_tokens": 4,
      "token_ids": [
        2,
        125697,
        12095,
        125716
      ],
      "tokens": [
        "<bos>",
        "د",
        "اق",
        "س"
      ]
    },
    {
      "text": "دراسة",
      "n_tokens": 4,
      "token_ids": [
        2,
        125697,
        2263,
        35319
      ],
      "tokens": [
        "<bos>",
        "د",
        "را",
        "سة"
      ]
    },
    {
      "text": "دروس",
      "n_tokens": 3,
      "token_ids": [
        2,
        125697,
        34017
      ],
      "tokens": [
        "<bos>",
        "د",
        "روس"
      ]
    },
    {
      "text": "دروع",
      "n_tokens": 3,
      "token_ids": [
        2,
        125697,
        44893
      ],
      "tokens": [
        "<bos>",
        "د",
        "روع"
      ]
    },
    {
      "text": "دغاز",
      "n_tokens": 3,
      "token_ids": [
        2,
        125697,
        68037
      ],
      "tokens": [
        "<bos>",
        "د",
        "غاز"
      ]
    },
    {
      "text": "دغوز",
      "n_tokens": 4,
      "token_ids": [
        2,
        125697,
        126036,
        11850
      ],
      "tokens": [
        "<bos>",
        "د",
        "غ",
        "وز"
      ]
    },
    {
      "text": "دقاس",
      "n_tokens": 4,
      "token_ids": [
        2,
        125697,
        125756,
        7146
      ],
      "tokens": [
        "<bos>",
        "د",
        "ق",
        "اس"
      ]
    },
    {
      "text": "دقوس",
      "n_tokens": 4,
      "token_ids": [
        2,
        125697,
        125756,
        12402
      ],
      "tokens": [
        "<bos>",
        "د",
        "ق",
        "وس"
      ]
    },
    {
      "text": "ذاحج",
      "n_tokens": 4,
      "token_ids": [
        2,
        11230,
        125769,
        125773
      ],
      "tokens": [
        "<bos>",
        "ذا",
        "ح",
        "ج"
      ]
    },
    {
      "text": "ذحاج",
      "n_tokens": 4,
      "token_ids": [
        2,
        126008,
        125769,
        15882
      ],
      "tokens": [
        "<bos>",
        "ذ",
        "ح",
        "اج"
      ]
    },
    {
      "text": "ذحوج",
      "n_tokens": 4,
      "token_ids": [
        2,
        126008,
        125769,
        14319
      ],
      "tokens": [
        "<bos>",
        "ذ",
        "ح",
        "وج"
      ]
    },
    {
      "text": "رمال",
      "n_tokens": 3,
      "token_ids": [
        2,
        12808,
        1821
      ],
      "tokens": [
        "<bos>",
        "رم",
        "ال"
      ]
    },
    {
      "text": "زعلان",
      "n_tokens": 3,
      "token_ids": [
        2,
        125770,
        100505
      ],
      "tokens": [
        "<bos>",
        "ز",
        "علان"
      ]
    },
    {
      "text": "زملاء",
      "n_tokens": 3,
      "token_ids": [
        2,
        26629,
        55352
      ],
      "tokens": [
        "<bos>",
        "زم",
        "لاء"
      ]
    },
    {
      "text": "سكران",
      "n_tokens": 3,
      "token_ids": [
        2,
        87701,
        1613
      ],
      "tokens": [
        "<bos>",
        "سكر",
        "ان"
      ]
    },
    {
      "text": "سلال",
      "n_tokens": 3,
      "token_ids": [
        2,
        125716,
        22682
      ],
      "tokens": [
        "<bos>",
        "س",
        "لال"
      ]
    },
    {
      "text": "سميك",
      "n_tokens": 3,
      "token_ids": [
        2,
        11488,
        14559
      ],
      "tokens": [
        "<bos>",
        "سم",
        "يك"
      ]
    },
    {
      "text": "شاظق",
      "n_tokens": 4,
      "token_ids": [
        2,
        71826,
        126210,
        125756
      ],
      "tokens": [
        "<bos>",
        "شا",
        "ظ",
        "ق"
      ]
    },
    {
      "text": "شاهد",
      "n_tokens": 2,
      "token_ids": [
        2,
        122183
      ],
      "tokens": [
        "<bos>",
        "شاهد"
      ]
    },
    {
      "text": "شركاء",
      "n_tokens": 4,
      "token_ids": [
        2,
        125746,
        17032,
        11373
      ],
      "tokens": [
        "<bos>",
        "ش",
        "رك",
        "اء"
      ]
    },
    {
      "text": "شروح",
      "n_tokens": 3,
      "token_ids": [
        2,
        125746,
        91577
      ],
      "tokens": [
        "<bos>",
        "ش",
        "روح"
      ]
    },
    {
      "text": "شروط",
      "n_tokens": 3,
      "token_ids": [
        2,
        125746,
        100920
      ],
      "tokens": [
        "<bos>",
        "ش",
        "روط"
      ]
    },
    {
      "text": "شظاق",
      "n_tokens": 4,
      "token_ids": [
        2,
        125746,
        126210,
        12095
      ],
      "tokens": [
        "<bos>",
        "ش",
        "ظ",
        "اق"
      ]
    },
    {
      "text": "شظوق",
      "n_tokens": 4,
      "token_ids": [
        2,
        125746,
        126210,
        12415
      ],
      "tokens": [
        "<bos>",
        "ش",
        "ظ",
        "وق"
      ]
    },
    {
      "text": "شعراء",
      "n_tokens": 3,
      "token_ids": [
        2,
        122975,
        26775
      ],
      "tokens": [
        "<bos>",
        "شع",
        "راء"
      ]
    },
    {
      "text": "شهادة",
      "n_tokens": 4,
      "token_ids": [
        2,
        125746,
        2634,
        25562
      ],
      "tokens": [
        "<bos>",
        "ش",
        "ها",
        "دة"
      ]
    },
    {
      "text": "شهور",
      "n_tokens": 3,
      "token_ids": [
        2,
        39325,
        3216
      ],
      "tokens": [
        "<bos>",
        "شه",
        "ور"
      ]
    },
    {
      "text": "صحيح",
      "n_tokens": 3,
      "token_ids": [
        2,
        125822,
        80008
      ],
      "tokens": [
        "<bos>",
        "ص",
        "حيح"
      ]
    },
    {
      "text": "صلابة",
      "n_tokens": 3,
      "token_ids": [
        2,
        13413,
        10883
      ],
      "tokens": [
        "<bos>",
        "صل",
        "ابة"
      ]
    },
    {
      "text": "صناعة",
      "n_tokens": 3,
      "token_ids": [
        2,
        125822,
        109099
      ],
      "tokens": [
        "<bos>",
        "ص",
        "ناعة"
      ]
    },
    {
      "text": "طاغد",
      "n_tokens": 4,
      "token_ids": [
        2,
        125849,
        109184,
        125697
      ],
      "tokens": [
        "<bos>",
        "ط",
        "اغ",
        "د"
      ]
    },
    {
      "text": "طالب",
      "n_tokens": 3,
      "token_ids": [
        2,
        125849,
        29840
      ],
      "tokens": [
        "<bos>",
        "ط",
        "الب"
      ]
    },
    {
      "text": "طغاد",
      "n_tokens": 4,
      "token_ids": [
        2,
        125849,
        126036,
        3369
      ],
      "tokens": [
        "<bos>",
        "ط",
        "غ",
        "اد"
      ]
    },
    {
      "text": "طغود",
      "n_tokens": 4,
      "token_ids": [
        2,
        125849,
        126036,
        4167
      ],
      "tokens": [
        "<bos>",
        "ط",
        "غ",
        "ود"
      ]
    },
    {
      "text": "طلاب",
      "n_tokens": 3,
      "token_ids": [
        2,
        51244,
        3482
      ],
      "tokens": [
        "<bos>",
        "طل",
        "اب"
      ]
    },
    {
      "text": "عازم",
      "n_tokens": 3,
      "token_ids": [
        2,
        125724,
        59284
      ],
      "tokens": [
        "<bos>",
        "ع",
        "ازم"
      ]
    },
    {
      "text": "عالم",
      "n_tokens": 3,
      "token_ids": [
        2,
        125724,
        12305
      ],
      "tokens": [
        "<bos>",
        "ع",
        "الم"
      ]
    },
    {
      "text": "عروض",
      "n_tokens": 3,
      "token_ids": [
        2,
        125724,
        91400
      ],
      "tokens": [
        "<bos>",
        "ع",
        "روض"
      ]
    },
    {
      "text": "عطشان",
      "n_tokens": 3,
      "token_ids": [
        2,
        97897,
        39054
      ],
      "tokens": [
        "<bos>",
        "عط",
        "شان"
      ]
    },
    {
      "text": "علماء",
      "n_tokens": 3,
      "token_ids": [
        2,
        20941,
        43155
      ],
      "tokens": [
        "<bos>",
        "عل",
        "ماء"
      ]
    },
    {
      "text": "عمال",
      "n_tokens": 2,
      "token_ids": [
        2,
        49668
      ],
      "tokens": [
        "<bos>",
        "عمال"
      ]
    },
    {
      "text": "عملاء",
      "n_tokens": 3,
      "token_ids": [
        2,
        21879,
        55352
      ],
      "tokens": [
        "<bos>",
        "عم",
        "لاء"
      ]
    },
    {
      "text": "عميق",
      "n_tokens": 3,
      "token_ids": [
        2,
        21879,
        49129
      ],
      "tokens": [
        "<bos>",
        "عم",
        "يق"
      ]
    },
    {
      "text": "غاشط",
      "n_tokens": 4,
      "token_ids": [
        2,
        126036,
        9297,
        125849
      ],
      "tokens": [
        "<bos>",
        "غ",
        "اش",
        "ط"
      ]
    },
    {
      "text": "غرقان",
      "n_tokens": 4,
      "token_ids": [
        2,
        126036,
        29361,
        1613
      ],
      "tokens": [
        "<bos>",
        "غ",
        "رق",
        "ان"
      ]
    },
    {
      "text": "غشاط",
      "n_tokens": 4,
      "token_ids": [
        2,
        126036,
        125746,
        14843
      ],
      "tokens": [
        "<bos>",
        "غ",
        "ش",
        "اط"
      ]
    },
    {
      "text": "غشوط",
      "n_tokens": 4,
      "token_ids": [
        2,
        126036,
        125746,
        46900
      ],
      "tokens": [
        "<bos>",
        "غ",
        "ش",
        "وط"
      ]
    },
    {
      "text": "غضبان",
      "n_tokens": 4,
      "token_ids": [
        2,
        126036,
        125957,
        37178
      ],
      "tokens": [
        "<bos>",
        "غ",
        "ض",
        "بان"
      ]
    },
    {
      "text": "فاجز",
      "n_tokens": 4,
      "token_ids": [
        2,
        125734,
        15882,
        125770
      ],
      "tokens": [
        "<bos>",
        "ف",
        "اج",
        "ز"
      ]
    },
    {
      "text": "فارغ",
      "n_tokens": 3,
      "token_ids": [
        2,
        108650,
        126036
      ],
      "tokens": [
        "<bos>",
        "فار",
        "غ"
      ]
    },
    {
      "text": "فاغش",
      "n_tokens": 4,
      "token_ids": [
        2,
        30082,
        126036,
        125746
      ],
      "tokens": [
        "<bos>",
        "فا",
        "غ",
        "ش"
      ]
    },
    {
      "text": "فجاز",
      "n_tokens": 4,
      "token_ids": [
        2,
        125734,
        125773,
        8109
      ],
      "tokens": [
        "<bos>",
        "ف",
        "ج",
        "از"
      ]
    },
    {
      "text": "فجوز",
      "n_tokens": 4,
      "token_ids": [
        2,
        125734,
        125773,
        11850
      ],
      "tokens": [
        "<bos>",
        "ف",
        "ج",
        "وز"
      ]
    },
    {
      "text": "فراسة",
      "n_tokens": 4,
      "token_ids": [
        2,
        125734,
        2263,
        35319
      ],
      "tokens": [
        "<bos>",
        "ف",
        "را",
        "سة"
      ]
    },
    {
      "text": "فرحان",
      "n_tokens": 4,
      "token_ids": [
        2,
        13455,
        125769,
        1613
      ],
      "tokens": [
        "<bos>",
        "فر",
        "ح",
        "ان"
      ]
    },
    {
      "text": "فروع",
      "n_tokens": 3,
      "token_ids": [
        2,
        125734,
        44893
      ],
      "tokens": [
        "<bos>",
        "ف",
        "روع"
      ]
    },
    {
      "text": "فصحاء",
      "n_tokens": 4,
      "token_ids": [
        2,
        125734,
        56466,
        11373
      ],
      "tokens": [
        "<bos>",
        "ف",
        "صح",
        "اء"
      ]
    },
    {
      "text": "فغاش",
      "n_tokens": 4,
      "token_ids": [
        2,
        125734,
        126036,
        9297
      ],
      "tokens": [
        "<bos>",
        "ف",
        "غ",
        "اش"
      ]
    },
    {
      "text": "فغوش",
      "n_tokens": 4,
      "token_ids": [
        2,
        125734,
        126036,
        12239
      ],
      "tokens": [
        "<bos>",
        "ف",
        "غ",
        "وش"
      ]
    },
    {
      "text": "قاهث",
      "n_tokens": 4,
      "token_ids": [
        2,
        125756,
        7241,
        126051
      ],
      "tokens": [
        "<bos>",
        "ق",
        "اه",
        "ث"
      ]
    },
    {
      "text": "قروض",
      "n_tokens": 3,
      "token_ids": [
        2,
        125756,
        91400
      ],
      "tokens": [
        "<bos>",
        "ق",
        "روض"
      ]
    },
    {
      "text": "قهاث",
      "n_tokens": 4,
      "token_ids": [
        2,
        125756,
        2634,
        126051
      ],
      "tokens": [
        "<bos>",
        "ق",
        "ها",
        "ث"
      ]
    },
    {
      "text": "قهوث",
      "n_tokens": 3,
      "token_ids": [
        2,
        21354,
        58178
      ],
      "tokens": [
        "<bos>",
        "قه",
        "وث"
      ]
    },
    {
      "text": "كاتب",
      "n_tokens": 2,
      "token_ids": [
        2,
        119562
      ],
      "tokens": [
        "<bos>",
        "كاتب"
      ]
    },
    {
      "text": "كاغف",
      "n_tokens": 4,
      "token_ids": [
        2,
        71138,
        126036,
        125734
      ],
      "tokens": [
        "<bos>",
        "كا",
        "غ",
        "ف"
      ]
    },
    {
      "text": "كبار",
      "n_tokens": 3,
      "token_ids": [
        2,
        125780,
        16403
      ],
      "tokens": [
        "<bos>",
        "ك",
        "بار"
      ]
    },
    {
      "text": "كبير",
      "n_tokens": 3,
      "token_ids": [
        2,
        125780,
        42352
      ],
      "tokens": [
        "<bos>",
        "ك",
        "بير"
      ]
    },
    {
      "text": "كتابة",
      "n_tokens": 3,
      "token_ids": [
        2,
        18626,
        10883
      ],
      "tokens": [
        "<bos>",
        "كت",
        "ابة"
      ]
    },
    {
      "text": "كثير",
      "n_tokens": 3,
      "token_ids": [
        2,
        125780,
        41354
      ],
      "tokens": [
        "<bos>",
        "ك",
        "ثير"
      ]
    },
    {
      "text": "كسلان",
      "n_tokens": 4,
      "token_ids": [
        2,
        125780,
        32018,
        1613
      ],
      "tokens": [
        "<bos>",
        "ك",
        "سل",
        "ان"
      ]
    },
    {
      "text": "كغاف",
      "n_tokens": 4,
      "token_ids": [
        2,
        125780,
        126036,
        8744
      ],
      "tokens": [
        "<bos>",
        "ك",
        "غ",
        "اف"
      ]
    },
    {
      "text": "كغوف",
      "n_tokens": 4,
      "token_ids": [
        2,
        125780,
        126036,
        16788
      ],
      "tokens": [
        "<bos>",
        "ك",
        "غ",
        "وف"
      ]
    },
    {
      "text": "لاعب",
      "n_tokens": 2,
      "token_ids": [
        2,
        58563
      ],
      "tokens": [
        "<bos>",
        "لاعب"
      ]
    },
    {
      "text": "لطفاء",
      "n_tokens": 4,
      "token_ids": [
        2,
        125673,
        37763,
        11373
      ],
      "tokens": [
        "<bos>",
        "ل",
        "طف",
        "اء"
      ]
    },
    {
      "text": "مادص",
      "n_tokens": 4,
      "token_ids": [
        2,
        125679,
        3369,
        125822
      ],
      "tokens": [
        "<bos>",
        "م",
        "اد",
        "ص"
      ]
    },
    {
      "text": "مبنوص",
      "n_tokens": 4,
      "token_ids": [
        2,
        125679,
        58854,
        28228
      ],
      "tokens": [
        "<bos>",
        "م",
        "بن",
        "وص"
      ]
    },
    {
      "text": "متدوغ",
      "n_tokens": 4,
      "token_ids": [
        2,
        22412,
        58976,
        126036
      ],
      "tokens": [
        "<bos>",
        "مت",
        "دو",
        "غ"
      ]
    },
    {
      "text": "مثموخ",
      "n_tokens": 4,
      "token_ids": [
        2,
        41113,
        43067,
        125792
      ],
      "tokens": [
        "<bos>",
        "مث",
        "مو",
        "خ"
      ]
    },
    {
      "text": "مجبوص",
      "n_tokens": 4,
      "token_ids": [
        2,
        64864,
        8617,
        125822
      ],
      "tokens": [
        "<bos>",
        "مج",
        "بو",
        "ص"
      ]
    },
    {
      "text": "مجراف",
      "n_tokens": 3,
      "token_ids": [
        2,
        64864,
        25421
      ],
      "tokens": [
        "<bos>",
        "مج",
        "راف"
      ]
    },
    {
      "text": "مجفوق",
      "n_tokens": 4,
      "token_ids": [
        2,
        64864,
        125734,
        12415
      ],
      "tokens": [
        "<bos>",
        "مج",
        "ف",
        "وق"
      ]
    },
    {
      "text": "محذوس",
      "n_tokens": 4,
      "token_ids": [
        2,
        33265,
        126008,
        12402
      ],
      "tokens": [
        "<bos>",
        "مح",
        "ذ",
        "وس"
      ]
    },
    {
      "text": "محراث",
      "n_tokens": 3,
      "token_ids": [
        2,
        33265,
        92260
      ],
      "tokens": [
        "<bos>",
        "مح",
        "راث"
      ]
    },
    {
      "text": "مخبار",
      "n_tokens": 3,
      "token_ids": [
        2,
        125679,
        99938
      ],
      "tokens": [
        "<bos>",
        "م",
        "خبار"
      ]
    },
    {
      "text": "مخترق",
      "n_tokens": 5,
      "token_ids": [
        2,
        125679,
        125792,
        6234,
        125756
      ],
      "tokens": [
        "<bos>",
        "م",
        "خ",
        "تر",
        "ق"
      ]
    },
    {
      "text": "مختلف",
      "n_tokens": 3,
      "token_ids": [
        2,
        125679,
        33927
      ],
      "tokens": [
        "<bos>",
        "م",
        "ختلف"
      ]
    },
    {
      "text": "مخفوص",
      "n_tokens": 5,
      "token_ids": [
        2,
        125679,
        125792,
        125734,
        28228
      ],
      "tokens": [
        "<bos>",
        "م",
        "خ",
        "ف",
        "وص"
      ]
    },
    {
      "text": "مداص",
      "n_tokens": 3,
      "token_ids": [
        2,
        12111,
        15836
      ],
      "tokens": [
        "<bos>",
        "مد",
        "اص"
      ]
    },
    {
      "text": "مدغوز",
      "n_tokens": 4,
      "token_ids": [
        2,
        12111,
        126036,
        11850
      ],
      "tokens": [
        "<bos>",
        "مد",
        "غ",
        "وز"
      ]
    },
    {
      "text": "مدقوس",
      "n_tokens": 4,
      "token_ids": [
        2,
        12111,
        125756,
        12402
      ],
      "tokens": [
        "<bos>",
        "مد",
        "ق",
        "وس"
      ]
    },
    {
      "text": "مدوص",
      "n_tokens": 3,
      "token_ids": [
        2,
        12111,
        28228
      ],
      "tokens": [
        "<bos>",
        "مد",
        "وص"
      ]
    },
    {
      "text": "مذحوج",
      "n_tokens": 5,
      "token_ids": [
        2,
        125679,
        126008,
        125769,
        14319
      ],
      "tokens": [
        "<bos>",
        "م",
        "ذ",
        "ح",
        "وج"
      ]
    },
    {
      "text": "مذكور",
      "n_tokens": 4,
      "token_ids": [
        2,
        125679,
        84775,
        3216
      ],
      "tokens": [
        "<bos>",
        "م",
        "ذك",
        "ور"
      ]
    },
    {
      "text": "مزمار",
      "n_tokens": 3,
      "token_ids": [
        2,
        48483,
        25885
      ],
      "tokens": [
        "<bos>",
        "مز",
        "مار"
      ]
    },
    {
      "text": "مسمار",
      "n_tokens": 4,
      "token_ids": [
        2,
        125679,
        11488,
        1897
      ],
      "tokens": [
        "<bos>",
        "م",
        "سم",
        "ار"
      ]
    },
    {
      "text": "مشترك",
      "n_tokens": 3,
      "token_ids": [
        2,
        35323,
        51587
      ],
      "tokens": [
        "<bos>",
        "مش",
        "ترك"
      ]
    },
    {
      "text": "مشروب",
      "n_tokens": 3,
      "token_ids": [
        2,
        35323,
        84589
      ],
      "tokens": [
        "<bos>",
        "مش",
        "روب"
      ]
    },
    {
      "text": "مشظوق",
      "n_tokens": 4,
      "token_ids": [
        2,
        35323,
        126210,
        12415
      ],
      "tokens": [
        "<bos>",
        "مش",
        "ظ",
        "وق"
      ]
    },
    {
      "text": "مصباح",
      "n_tokens": 4,
      "token_ids": [
        2,
        125679,
        31337,
        12332
      ],
      "tokens": [
        "<bos>",
        "م",
        "صب",
        "اح"
      ]
    },
    {
      "text": "مصنوع",
      "n_tokens": 3,
      "token_ids": [
        2,
        71118,
        53013
      ],
      "tokens": [
        "<bos>",
        "مص",
        "نوع"
      ]
    },
    {
      "text": "مطغود",
      "n_tokens": 4,
      "token_ids": [
        2,
        85481,
        126036,
        4167
      ],
      "tokens": [
        "<bos>",
        "مط",
        "غ",
        "ود"
      ]
    },
    {
      "text": "معترض",
      "n_tokens": 4,
      "token_ids": [
        2,
        13394,
        6234,
        125957
      ],
      "tokens": [
        "<bos>",
        "مع",
        "تر",
        "ض"
      ]
    },
    {
      "text": "معترف",
      "n_tokens": 3,
      "token_ids": [
        2,
        13394,
        117591
      ],
      "tokens": [
        "<bos>",
        "مع",
        "ترف"
      ]
    },
    {
      "text": "معروف",
      "n_tokens": 3,
      "token_ids": [
        2,
        13394,
        37614
      ],
      "tokens": [
        "<bos>",
        "مع",
        "روف"
      ]
    },
    {
      "text": "مغشوط",
      "n_tokens": 5,
      "token_ids": [
        2,
        125679,
        126036,
        125746,
        46900
      ],
      "tokens": [
        "<bos>",
        "م",
        "غ",
        "ش",
        "وط"
      ]
    },
    {
      "text": "مغمور",
      "n_tokens": 4,
      "token_ids": [
        2,
        125679,
        54871,
        3216
      ],
      "tokens": [
        "<bos>",
        "م",
        "غم",
        "ور"
      ]
    },
    {
      "text": "مفتاح",
      "n_tokens": 4,
      "token_ids": [
        2,
        125679,
        11333,
        12332
      ],
      "tokens": [
        "<bos>",
        "م",
        "فت",
        "اح"
      ]
    },
    {
      "text": "مفتوح",
      "n_tokens": 4,
      "token_ids": [
        2,
        125679,
        11333,
        54613
      ],
      "tokens": [
        "<bos>",
        "م",
        "فت",
        "وح"
      ]
    },
    {
      "text": "مفجوز",
      "n_tokens": 5,
      "token_ids": [
        2,
        125679,
        125734,
        125773,
        11850
      ],
      "tokens": [
        "<bos>",
        "م",
        "ف",
        "ج",
        "وز"
      ]
    },
    {
      "text": "مفغوش",
      "n_tokens": 5,
      "token_ids": [
        2,
        125679,
        125734,
        126036,
        12239
      ],
      "tokens": [
        "<bos>",
        "م",
        "ف",
        "غ",
        "وش"
      ]
    },
    {
      "text": "مقترح",
      "n_tokens": 4,
      "token_ids": [
        2,
        111296,
        6234,
        125769
      ],
      "tokens": [
        "<bos>",
        "مق",
        "تر",
        "ح"
      ]
    },
    {
      "text": "مقتنع",
      "n_tokens": 4,
      "token_ids": [
        2,
        125679,
        20181,
        75637
      ],
      "tokens": [
        "<bos>",
        "م",
        "قت",
        "نع"
      ]
    },
    {
      "text": "مقلاع",
      "n_tokens": 3,
      "token_ids": [
        2,
        111296,
        45319
      ],
      "tokens": [
        "<bos>",
        "مق",
        "لاع"
      ]
    },
    {
      "text": "مقهوث",
      "n_tokens": 4,
      "token_ids": [
        2,
        125679,
        21354,
        58178
      ],
      "tokens": [
        "<bos>",
        "م",
        "قه",
        "وث"
      ]
    },
    {
      "text": "مكتوب",
      "n_tokens": 4,
      "token_ids": [
        2,
        125679,
        18626,
        10068
      ],
      "tokens": [
        "<bos>",
        "م",
        "كت",
        "وب"
      ]
    },
    {
      "text": "مكغوف",
      "n_tokens": 4,
      "token_ids": [
        2,
        113695,
        126036,
        16788
      ],
      "tokens": [
        "<bos>",
        "مك",
        "غ",
        "وف"
      ]
    },
    {
      "text": "ملفوف",
      "n_tokens": 4,
      "token_ids": [
        2,
        10436,
        125734,
        16788
      ],
      "tokens": [
        "<bos>",
        "مل",
        "ف",
        "وف"
      ]
    },
    {
      "text": "ممدوص",
      "n_tokens": 4,
      "token_ids": [
        2,
        125679,
        12111,
        28228
      ],
      "tokens": [
        "<bos>",
        "م",
        "مد",
        "وص"
      ]
    },
    {
      "text": "منتحر",
      "n_tokens": 4,
      "token_ids": [
        2,
        7396,
        32294,
        125677
      ],
      "tokens": [
        "<bos>",
        "من",
        "تح",
        "ر"
      ]
    },
    {
      "text": "منتظم",
      "n_tokens": 3,
      "token_ids": [
        2,
        79477,
        46106
      ],
      "tokens": [
        "<bos>",
        "منت",
        "ظم"
      ]
    },
    {
      "text": "منتفع",
      "n_tokens": 3,
      "token_ids": [
        2,
        79477,
        33041
      ],
      "tokens": [
        "<bos>",
        "منت",
        "فع"
      ]
    },
    {
      "text": "منزوع",
      "n_tokens": 4,
      "token_ids": [
        2,
        7396,
        125770,
        13293
      ],
      "tokens": [
        "<bos>",
        "من",
        "ز",
        "وع"
      ]
    },
    {
      "text": "منشار",
      "n_tokens": 3,
      "token_ids": [
        2,
        7396,
        20299
      ],
      "tokens": [
        "<bos>",
        "من",
        "شار"
      ]
    },
    {
      "text": "منظار",
      "n_tokens": 4,
      "token_ids": [
        2,
        7396,
        126210,
        1897
      ],
      "tokens": [
        "<bos>",
        "من",
        "ظ",
        "ار"
      ]
    },
    {
      "text": "منفوغ",
      "n_tokens": 4,
      "token_ids": [
        2,
        7396,
        102094,
        126036
      ],
      "tokens": [
        "<bos>",
        "من",
        "فو",
        "غ"
      ]
    },
    {
      "text": "مهدود",
      "n_tokens": 4,
      "token_ids": [
        2,
        125679,
        14370,
        4167
      ],
      "tokens": [
        "<bos>",
        "م",
        "هد",
        "ود"
      ]
    },
    {
      "text": "مهزوخ",
      "n_tokens": 4,
      "token_ids": [
        2,
        25191,
        83434,
        125792
      ],
      "tokens": [
        "<bos>",
        "مه",
        "زو",
        "خ"
      ]
    },
    {
      "text": "نافغ",
      "n_tokens": 3,
      "token_ids": [
        2,
        115946,
        126036
      ],
      "tokens": [
        "<bos>",
        "ناف",
        "غ"
      ]
    },
    {
      "text": "نبهاء",
      "n_tokens": 3,
      "token_ids": [
        2,
        65243,
        94051
      ],
      "tokens": [
        "<bos>",
        "نب",
        "هاء"
      ]
    },
    {
      "text": "ندمان",
      "n_tokens": 3,
      "token_ids": [
        2,
        3946,
        9667
      ],
      "tokens": [
        "<bos>",
        "ند",
        "مان"
      ]
    },
    {
      "text": "نظيف",
      "n_tokens": 3,
      "token_ids": [
        2,
        67543,
        14348
      ],
      "tokens": [
        "<bos>",
        "نظ",
        "يف"
      ]
    },
    {
      "text": "نعسان",
      "n_tokens": 3,
      "token_ids": [
        2,
        75637,
        30706
      ],
      "tokens": [
        "<bos>",
        "نع",
        "سان"
      ]
    },
    {
      "text": "نفاغ",
      "n_tokens": 4,
      "token_ids": [
        2,
        125681,
        30082,
        126036
      ],
      "tokens": [
        "<bos>",
        "ن",
        "فا",
        "غ"
      ]
    },
    {
      "text": "نفوغ",
      "n_tokens": 4,
      "token_ids": [
        2,
        71296,
        125683,
        126036
      ],
      "tokens": [
        "<bos>",
        "نف",
        "و",
        "غ"
      ]
    },
    {
      "text": "هارب",
      "n_tokens": 3,
      "token_ids": [
        2,
        125706,
        81338
      ],
      "tokens": [
        "<bos>",
        "ه",
        "ارب"
      ]
    },
    {
      "text": "هازخ",
      "n_tokens": 3,
      "token_ids": [
        2,
        68310,
        125792
      ],
      "tokens": [
        "<bos>",
        "هاز",
        "خ"
      ]
    },
    {
      "text": "هزاخ",
      "n_tokens": 4,
      "token_ids": [
        2,
        125706,
        125770,
        20776
      ],
      "tokens": [
        "<bos>",
        "ه",
        "ز",
        "اخ"
      ]
    },
    {
      "text": "هزوخ",
      "n_tokens": 4,
      "token_ids": [
        2,
        125706,
        83434,
        125792
      ],
      "tokens": [
        "<bos>",
        "ه",
        "زو",
        "خ"
      ]
    }
  ]
}